<?xml version="1.0" encoding="utf-8"?>
<IncrementalBankBuild Version="6" Flags="601859981">
	<Platform GUID="{6EE13744-B82F-456A-BB7B-80D2AACACB8A}">
		<Banks>
			<Language ID="393239870">
				<File Name="Init" Hash="2371146297" Timestamp="1547894591"/>
				<File Name="Main" Hash="923882846" Timestamp="1547912133"/>
			</Language>
		</Banks>
		<XMLInfo>
			<Language ID="-1">
				<File Name="" Hash="2438323485" Timestamp="1547912133"/>
			</Language>
		</XMLInfo>
	</Platform>
</IncrementalBankBuild>
